Workbook

Sheet Drivers, Inputs and Outputs
B1: Drivers and Inputs
B2: All figures in USD millions unless stated | E2: 44592 | F2: =EDATE(E2,12) -> 44957 | G2: =EDATE(F2,12) -> 45322 | H2: =EDATE(G2,12) -> 45688 | I2: =EDATE(H2,12) -> 46053 | J2: =EDATE(I2,12) -> 46418 | K2: =EDATE(J2,12) -> 46783 | L2: =EDATE(K2,12) -> 47149 | M2: =EDATE(L2,12) -> 47514 | N2: =EDATE(M2,12) -> 47879 | O2: Term
B4: Growth Rate | J4: 0.05 | K4: 0.0525 | L4: 0.0525 | M4: 0.055 | N4: 0.0575 | O4: 0.06 | Q4: Aggregate Growth rate taken from Earnings report and previous trend
B6: Cost of Sales | J6: 0.75 | K6: 0.7495 | L6: 0.749 | M6: 0.7485 | N6: 0.748 | O6: 0.7475 | Q6: Assumed to reduce to match with historical years and might increase during distress times like in 2023 cause of Russia - Ukraine conflict
B8: SG&A | J8: 0.205 | K8: 0.2045 | L8: 0.204 | M8: 0.2035 | N8: 0.203 | O8: 0.2025 | Q8: Assumed to reduce slowly in line with historicals as previous years registers similar figures in range of 20%
B10: CapEx | J10: =Model!K7*Model!K584 -> 28119.832 | K10: =Model!L7*Model!L584 -> 31616.838 | L10: =Model!M7*Model!M584 -> 33330.972 | M10: =Model!N7*Model!N584 -> 37427.195 | N10: =Model!O7*Model!O584 -> 39652.939 | O10: =Model!P7*Model!P584 -> 0 | Q10: Assumes only 3.5% of Rev to closely match with the historicals
B12: Accounts Recievables Days | J12: 5.6 | K12: 5.5 | L12: 5.4 | M12: 5.3 | N12: 5.2 | O12: 5.1 | Q12: Assuming that AR days might improve gradually towards 5 days
B13: Invetory Days | J13: 40 | K13: 39.5 | L13: 39 | M13: 38.5 | N13: 38 | O13: 37.5 | Q13: Assuming that Inventory days will improve matching the trend and might hover around 38 in the future but shown will improve matching the trend
B14: Accounts Payable Days | J14: 42.25 | K14: 42.5 | L14: 42.5 | M14: 42.75 | N14: 43 | O14: 43.25 | Q14: Assumed to improve again as it fluctuates between 42 to 43
B18: Taxes | J18: Assets & Depreciation
B20: Tax Rate | G20: 0.245 | J20: First Year Accounting Depreciation/ Depreciable First year Amount | O20: 0.5 | Q20: Tax rate is in the range 24% to 25% as mentioned in the report
B21: First Year Tax Depreciation | G21: 0.3 | J21: Usefull life: Existing assets | O21: 15 | Q21: Tax Basis for assets is calculated using (
B22: Blended tax Depreciation Rate | G22: 0.15 | J22: Usefull life: New assets | O22: 12
B23: Tax basis for Assets | G23: =(Model!J270-(Notes!G28/'Drivers, Inputs and Outputs'!G20)) -> 111095.24 | H23: end of 2026 | Q23: For Tax Basis for assets is calculated using the formula (net ppe- (DTL ppe/tax rate))basically back solving the using formula used to claculate the DTL
B24: Tax Losses | G24: 0 | H24: end of 2026 | J24: Net PP&E at the End of 2026FY | O24: =Notes!G11 -> 136083 | Q24: NO Tax losses as Walmart been genrating good taxable income meaning they are profitable assuming zero for tax losses.
J25: Gross PP&E at the End of 2026FY | O25: =Notes!G9 -> 256421
J26: Depreciable Assets | O26: 216939
B28: Interest Rates | J28: Leases
B30: Cash Balances | G30: 0.02 | J30: Op Lease Weighted Avg Discount Rate | O30: 0.067 | Q30: Assumed to be Constant at 2026FY Discount Rate
B31: Revolving Credit Line | G31: 0.0475 | J31: Finance Weighted Avg Discount Rate | O31: 0.07
B32: Long Term Debt | G32: 0.05
B33: Short term Debt | G33: 0.0425 | J33: New Op Leases | O33: 2303 | Q33: New leases (OP and Finance) as on 2026FY and assumed to grow each year by 3.5% pa from 2027FY
J34: New Finance Lease | O34: 703
B35: Dates
J36: Other Single Inputs
B37: Valuation Date | G37: 46174
B38: First Expected Cash Flow | G38: 46234 | J38: Dividend Payout ratio | O38: 0.34
B39: First Fiscal Year End for Forecast | G39: 46418 | J39: NCI Dividend/Distribution | O39: 0.5
B40: First Year of Forecast | G40: 2026 | J40: Total Debt | O40: =Model!J95+Model!J101+Model!J103 -> 51523
B41: Incorrect Date Set for Valuation? | G41: =IF(G37>G38,1,0) -> 0 | J41: Cash | O41: =Model!J81 -> 10727
B42: Incorrect Date Set for First Cash Flow? | G42: =IF(G38>G39,1,0) -> 0 | J42: Market Capitalization | O42: 797240.25
B43: Days in Period | G43: 365
B48: Weighted Average Cost of Capital
K50: Average | L50: Debt/ | M50: Debt/ | N50: Levered | O50: Unlevered
B51: Name | E51: Exchange | F51: Ticker | G51: Region | I51: Debt | J51: Equity | K51: Tax Rate 1 | L51: Equity | M51: Capital | N51: Beta 2 | O51: Beta 3
B53: Costco Wholesale | E53: NYSE | F53: COST | G53: US | I53: 8132 | J53: 445290 | K53: 0.2497 | L53: =I53/J53 -> 0.018262256 | M53: =I53/(I53+J53) -> 0.017934727 | N53: 0.87 | O53: =N53/(1+(1-K53)*L53) -> 0.85824025
B54: Target Corporation | E54: NYSE | F54: TGT | G54: US | I54: 19420 | J54: 66150 | K54: 0.221 | L54: =I54/J54 -> 0.29357521 | M54: =I54/(I54+J54) -> 0.2269487 | N54: 1.01 | O54: =N54/(1+(1-K54)*L54) -> 0.82201029
B55: The Kroger Co | E55: NYSE | F55: KR | G55: US | I55: 24692 | J55: 39800 | K55: 0.235 | L55: =I55/J55 -> 0.62040201 | M55: =I55/(I55+J55) -> 0.38286919 | N55: 0.42 | O55: =N55/(1+(1-K55)*L55) -> 0.28482155
B56: Amazon.com Inc | E56: NASDAQ | F56: AMZN | G56: US | I56: 138500 | J56: 2500000 | K56: 0.195 | L56: =I56/J56 -> 0.0554 | M56: =I56/(I56+J56) -> 0.052491946 | Q56: Excluded to capture the grocery focused business to calculate the WACC
Q57: As Wlamart is transitioning into more like Amazon but retail at its core
J59: Average | K59: =AVERAGE(K53:K56) -> 0.225175 | L59: =AVERAGE(L53:L56) -> 0.24690987 | M59: =AVERAGE(M53:M56) -> 0.17006114 | N59: =AVERAGE(N53:N56) -> 0.76666667 | O59: =AVERAGE(O53:O56) -> 0.65502403
J60: Median | K60: =MEDIAN(K53:K56) -> 0.228 | L60: =MEDIAN(L53:L56) -> 0.1744876 | M60: =MEDIAN(M53:M56) -> 0.13972032 | N60: =MEDIAN(N53:N56) -> 0.87 | O60: =MEDIAN(O53:O56) -> 0.82201029
B63: Risk Premium for Equity | K63: Cost of Equity
B65: Market Risk Premium | G65: 0.044 | K65: Risk Free Rate | O65: 0.0416 | Q65: 10Y Treasury Notes as on 1st June 2026 is 4.16%
B66: Average Unlevered Beta | G66: =O59 -> 0.65502403 | K66: Equity Risk Premium | O66: =G68 -> 0.030209987
B67: Levered Beta 4 | G67: =G66*(1+(1-O75)*G78) -> 0.68659061 | K67: Country Risk Premium | O67: 0 | Q67: Considered as 0 since it’s a Benchamark Matured Market
B68: Equity Risk Premium | G68: =G67*G65 -> 0.030209987 | K68: Cost of Equity | O68: =SUM(O65:O67) -> 0.071809987
Q69: MRP (4.3% to 4.5%) : Based on model-agnostic implied equity risk premium valuations for the S&P 500, the market risk premium hovered in the mid-4% range. This reflects the incremental return investors required above the risk-free rate to hold a diversified portfolio of equities amidst mid-year geopolitical volatility
Q70: from Ashwath Damodaran
B72: Capital Structure | K72: Cost of Debt
F73: Current | G73: Target
B74: Total Debt | E74: =O40 -> 51523 | F74: =E74/E76 -> 0.060703618 | G74: 0.06 | K74: Pre-Tax Cost of Debt | O74: =O65+0.65% -> 0.0481 | Q74: Benchmark Rate (10Y treasury) + Credit Spread
B75: Market Capitalization | E75: =O42 -> 797240.25 | F75: =E75/E76 -> 0.93929638 | G75: =1-G74 -> 0.94 | K75: Tax Rate | O75: =G20 -> 0.245 | Q75: 4.16% + 0.65% | S75: 0.6% to 0.7% for AA rated company like Walmart
B76: Total Capitalization | E76: =SUM(E74:E75) -> 848763.25 | F76: =SUM(F74:F75) -> 1 | G76: =SUM(G74:G75) -> 1 | K76: After-Tax Cost of Debt | O76: =O74*(1-O75) -> 0.0363155 | Q76: In recent bond offerings, Walmart's 10-year tranches have been priced at exactly 0.70% above U.S. Treasuries.
Q77: For highly rated 'AA' corporate issuers like Walmart, the spread typically fluctuates between 0.45% and 0.75% depending on daily market volatility and the specific maturity of the debt.
B78: Debt / Equity | F78: =F74/F75 -> 0.064626692 | G78: =G74/G75 -> 0.063829787
B81: NOTE: | K81: Weighted Average Cost of Capital | Q81: Treating Walmart as like a tech company or as a hybrid following are the peers:
B82: Tax Rate is a 5-Year Average. | N82: Weight | O82: Cost | Q82: Amazon AMZN
B83: Levered beta is based on 5-year monthly data. | K83: Debt Capital | N83: =G74 -> 0.06 | O83: =O76 -> 0.0363155 | Q83: Costco wholesale COST
B84: Unlevered Beta = Levered Beta / (1 + (1 - Tax Rate) × Debt-to-Equity) | K84: Equity Capital | N84: =G75 -> 0.94 | O84: =O68 -> 0.071809987 | Q84: Alphabet INC GOOGL
B85: Levered Beta = Unlevered Beta x (1 + (1 - Tax rate) x (Debt-to-Equity)) | Q85: The Home Depot HD
Q86: Meta Platforms META
Q87: *similar to Walamrt transition from traditional retailer to a business encompasing modern digital reach
K88: Weighted Average Cost of Capital | O88: =SUMPRODUCT(N83:N84,O83:O84) -> 0.069680318
B89: Valuation Input and Assumptions
B91: Net Debt | G91: 40796
B92: Shares Oustanding | E92: (FD 000) | G92: 7971
B93: Current Stock Price | E93: (US$/sh) | G93: 114.58 | Q93: AS on 1st June 2026
B94: Terminal Growth Rate | G94: 0.03 | Q94: Grocery-Ecom-Tech hybrid TV ranging from 2.5% to 3.5%
B95: Terminal EBITDA Multiple | G95: 11 | Q95: only Grocery 2 % to 3% is justified
B96: Weighted Average Cost of Capital | G96: =O88 -> 0.069680318 | Q96: Since the Walmrt is in both matured state in Grocery and in transition with the technology and certain supply chain and Ai driven tech in being inplemented so assuming 3%
B97: Terminal Growth Greater than or equal to WACC | G97: =IF(G94>G96,1,0) -> 0
B102: Dashboard and Outputs
D107: EnterPrise Value | L107: Equity Value per Share
F109: Terminal Growth value | N109: Terminal Growth value
C110: =Model!J638 -> 817660.72 | D110: =Model!D709 -> 0.025 | E110: =Model!E709 -> 0.0275 | F110: =Model!F709 -> 0.03 | G110: =Model!G709 -> 0.0325 | H110: =Model!H709 -> 0.035 | L110: =D120 -> 0.025 | M110: =E120 -> 0.0275 | N110: =F120 -> 0.03 | O110: =G120 -> 0.0325 | P110: =H120 -> 0.035
B111: WACC | C111: =Model!C710 -> 0.065 | D111: =Model!D710 -> 826091.07 | E111: =Model!E710 -> 876040.88 | F111: =Model!F710 -> 933126.37 | G111: =Model!G710 -> 998994.24 | H111: =Model!H710 -> 1075840.1 | J111: WACC | K111: =C121 -> 0.065 | L111: =D121/$G$92 -> 98.519016 | M111: =E121/$G$92 -> 104.78546 | N111: =F121/$G$92 -> 111.9471 | O111: =G121/$G$92 -> 120.21054 | P111: =H121/$G$92 -> 129.85122
C112: =Model!C711 -> 0.0675 | D112: =Model!D711 -> 774726.17 | E112: =Model!E711 -> 818371 | F112: =Model!F711 -> 867835.15 | G112: =Model!G711 -> 924365.6 | H112: =Model!H711 -> 989593.04 | K112: =C122 -> 0.0675 | L112: =D122/$G$92 -> 92.075043 | M112: =E122/$G$92 -> 97.550496 | N112: =F122/$G$92 -> 103.75601 | O112: =G122/$G$92 -> 110.84802 | P112: =H122/$G$92 -> 119.03112
C113: =Model!C712 -> 0.069680318 | D113: =Model!D712 -> 734649.74 | E113: =Model!E712 -> 773685.54 | F113: =Model!F712 -> 817640.12 | G113: =Model!G712 -> 867505.71 | H113: =Model!H712 -> 924560.62 | K113: =C123 -> 0.069680318 | L113: =D123/$G$92 -> 87.047263 | M113: =E123/$G$92 -> 91.944491 | N113: =F123/$G$92 -> 97.458803 | O113: =G123/$G$92 -> 103.71468 | P113: =H123/$G$92 -> 110.87249
C114: =Model!C713 -> 0.0725 | D114: =Model!D713 -> 688312.36 | E114: =Model!E713 -> 722354.66 | F114: =Model!F713 -> 760401.93 | G114: =Model!G713 -> 803205.1 | H114: =Model!H713 -> 851715.37 | K114: =C124 -> 0.0725 | L114: =D124/$G$92 -> 81.234019 | M114: =E124/$G$92 -> 85.504787 | N114: =F124/$G$92 -> 90.277998 | O114: =G124/$G$92 -> 95.647861 | P114: =H124/$G$92 -> 101.73371
C115: =Model!C714 -> 0.075 | D115: =Model!D714 -> 651631.02 | E115: =Model!E714 -> 681973.26 | F115: =Model!F714 -> 715686.87 | G115: =Model!G714 -> 753366.78 | H115: =Model!H714 -> 795756.67 | K115: =C125 -> 0.075 | L115: =D125/$G$92 -> 76.632169 | M115: =E125/$G$92 -> 80.438749 | N115: =F125/$G$92 -> 84.668281 | O115: =G125/$G$92 -> 89.395405 | P115: =H125/$G$92 -> 94.71342
D117: Equity Value | L117: Premium (Discount) to Stock price
F119: Terminal Growth value | N119: Terminal Growth value
D120: =D110 -> 0.025 | E120: =E110 -> 0.0275 | F120: =F110 -> 0.03 | G120: =G110 -> 0.0325 | H120: =H110 -> 0.035 | L120: =D120 -> 0.025 | M120: =E120 -> 0.0275 | N120: =F120 -> 0.03 | O120: =G120 -> 0.0325 | P120: =H120 -> 0.035
B121: WACC | C121: =C111 -> 0.065 | D121: =D111-$G$91 -> 785295.07 | E121: =E111-$G$91 -> 835244.88 | F121: =F111-$G$91 -> 892330.37 | G121: =G111-$G$91 -> 958198.24 | H121: =H111-$G$91 -> 1035044.1 | J121: WACC | K121: =C121 -> 0.065 | L121: =L111/$G$93-1 -> -0.14017267 | M121: =M111/$G$93-1 -> -0.085482137 | N121: =N111/$G$93-1 -> -0.02297867 | O121: =O111/$G$93-1 -> 0.049140714 | P121: =P111/$G$93-1 -> 0.13327999
C122: =C112 -> 0.0675 | D122: =D112-$G$91 -> 733930.17 | E122: =E112-$G$91 -> 777575 | F122: =F112-$G$91 -> 827039.15 | G122: =G112-$G$91 -> 883569.6 | H122: =H112-$G$91 -> 948797.04 | K122: =C122 -> 0.0675 | L122: =L112/$G$93-1 -> -0.19641261 | M122: =M112/$G$93-1 -> -0.14862545 | N122: =N112/$G$93-1 -> -0.094466668 | O122: =O112/$G$93-1 -> -0.032570919 | P122: =P112/$G$93-1 -> 0.038847252
C123: =C113 -> 0.069680318 | D123: =D113-$G$91 -> 693853.74 | E123: =E113-$G$91 -> 732889.54 | F123: =F113-$G$91 -> 776844.12 | G123: =G113-$G$91 -> 826709.71 | H123: =H113-$G$91 -> 883764.62 | K123: =C123 -> 0.069680318 | L123: =L113/$G$93-1 -> -0.24029269 | M123: =M113/$G$93-1 -> -0.19755201 | N123: =N113/$G$93-1 -> -0.1494257 | O123: =O113/$G$93-1 -> -0.094827374 | P123: =P113/$G$93-1 -> -0.03235739
C124: =C114 -> 0.0725 | D124: =D114-$G$91 -> 647516.36 | E124: =E114-$G$91 -> 681558.66 | F124: =F114-$G$91 -> 719605.93 | G124: =G114-$G$91 -> 762409.1 | H124: =H114-$G$91 -> 810919.37 | K124: =C124 -> 0.0725 | L124: =L114/$G$93-1 -> -0.29102794 | M124: =M114/$G$93-1 -> -0.2537547 | N124: =N114/$G$93-1 -> -0.21209637 | O124: =O114/$G$93-1 -> -0.16523074 | P124: =P114/$G$93-1 -> -0.11211637
C125: =C115 -> 0.075 | D125: =D115-$G$91 -> 610835.02 | E125: =E115-$G$91 -> 641177.26 | F125: =F115-$G$91 -> 674890.87 | G125: =G115-$G$91 -> 712570.78 | H125: =H115-$G$91 -> 754960.67 | K125: =C125 -> 0.075 | L125: =L115/$G$93-1 -> -0.3311907 | M125: =M115/$G$93-1 -> -0.29796868 | N125: =N115/$G$93-1 -> -0.26105532 | O125: =O115/$G$93-1 -> -0.21979922 | P125: =P115/$G$93-1 -> -0.1733861

Sheet Model
B1: Income Statement | R1: Notes Col
B2: All figures in million $
F3: 44592 | G3: =EDATE(F3,12) -> 44957 | H3: =EDATE(G3,12) -> 45322 | I3: =EDATE(H3,12) -> 45688 | J3: =EDATE(I3,12) -> 46053 | K3: =EDATE(J3,12) -> 46418 | L3: =EDATE(K3,12) -> 46783 | M3: =EDATE(L3,12) -> 47149 | N3: =EDATE(M3,12) -> 47514 | O3: =EDATE(N3,12) -> 47879 | P3: Term
B5: Net sales | F5: 567762 | G5: 605881 | H5: 642637 | I5: 674538 | J5: 706413 | K5: =K162 -> 742757.8 | L5: =L162 -> 782925.83 | M5: =M162 -> 825366.96 | N5: =N162 -> 872277.87 | O5: =O162 -> 924146.59 | P5: =P162 -> 981526.54
B6: Membership and Other Income | F6: 4992 | G6: 5408 | H6: 5488 | I6: 6447 | J6: 6750 | K6: =K163 -> 7104.375 | L6: =L163 -> 7495.1156 | M6: =M163 -> 7907.347 | N6: =N163 -> 8362.0194 | O6: =O163 -> 8863.7406 | P6: =P163 -> 9417.7244
B7: Total Revenue | F7: 572754 | G7: 611289 | H7: 648125 | I7: 680985 | J7: 713163 | K7: =SUM(K5:K6) -> 749862.18 | L7: =SUM(L5:L6) -> 790420.95 | M7: =SUM(M5:M6) -> 833274.3 | N7: =SUM(N5:N6) -> 880639.89 | O7: =SUM(O5:O6) -> 933010.33 | P7: =SUM(P5:P6) -> 990944.27
B9: Cost of Sales | F9: -429000 | G9: -463721 | H9: -490142 | I9: -511753 | J9: -535395 | K9: =K182*-1 -> -562396.63 | L9: =L182*-1 -> -592420.5 | M9: =M182*-1 -> -624122.45 | N9: =N182*-1 -> -659158.96 | O9: =O182*-1 -> -697891.73 | P9: =P182*-1 -> -740730.84
B10: SG&A | F10: -117812 | G10: -127140 | H10: -130971 | I10: -139884 | J10: -147943 | K10: =K183*-1 -> -153721.75 | L10: =L183*-1 -> -161641.08 | M10: =M183*-1 -> -169987.96 | N10: =N183*-1 -> -179210.22 | O10: =O183*-1 -> -189401.1 | P10: =P183*-1 -> -200666.21
B11: Operating Income | F11: 25942 | G11: 20428 | H11: 27012 | I11: 29348 | J11: 29825 | K11: =K7+K9+K10 -> 33743.798 | L11: =L7+L9+L10 -> 36359.364 | M11: =M7+M9+M10 -> 39163.892 | N11: =N7+N9+N10 -> 42270.715 | O11: =O7+O9+O10 -> 45717.506 | P11: =P7+P9+P10 -> 49547.213
B13: Interest Expense, Debt | F13: -16742 | G13: -1787 | H13: -2259 | I13: -2249 | J13: -2318 | K13: =K427 -> -2210.7675 | L13: =L427 -> -2253.1363 | M13: =M427 -> -2294.5487 | N13: =N427 -> -2329.1238 | O13: =O427 -> -2358.7675 | P13: =P427 -> -2375.0175
B14: Interest Expense, Financial lease | F14: -320 | G14: -341 | H14: -424 | I14: -479 | J14: -481 | K14: =K428*-1*-1 -> -473.27 | L14: =L428*-1*-1 -> -493.71385 | M14: =M428*-1*-1 -> -516.64628 | N14: =N428*-1*-1 -> -543.06443 | O14: =O428*-1*-1 -> -574.46582 | P14: =P428*-1*-1 -> 0
B15: Interest Income | F15: 158 | G15: 254 | H15: 546 | I15: 483 | J15: 368 | K15: =K429 -> 198.64009 | L15: =L429 -> 226.92026 | M15: =M429 -> 265.48972 | N15: =N429 -> 305.70289 | O15: =O429 -> 519.16736 | P15: =P429 -> 519.16736
B16: Net Interest | F16: -1836 | G16: -1874 | H16: -2137 | I16: -2245 | J16: -2431 | K16: =SUM(K13:K15) -> -2485.3974 | L16: =SUM(L13:L15) -> -2519.9298 | M16: =SUM(M13:M15) -> -2545.7053 | N16: =SUM(N13:N15) -> -2566.4853 | O16: =SUM(O13:O15) -> -2414.066 | P16: =SUM(P13:P15) -> -1855.8501
B17: loss on estinguishment of debt | F17: -2410 | G17: 0 | H17: 0 | I17: 0 | J17: 0 | K17: 0 | L17: 0 | M17: 0 | N17: 0 | O17: 0 | P17: 0
B19: Other gains/ (losses) | F19: -3000 | G19: -1538 | H19: -3027 | I19: -794 | J19: 2075 | K19: =K548 -> 0 | L19: =L548 -> 0 | M19: =M548 -> 0 | N19: =N548 -> 0 | O19: =O548 -> 0 | P19: =P548 -> 0 | R19: might consider an average value but for now its 0
B20: Income before Income taxes | F20: 18696 | G20: 17016 | H20: 21848 | I20: 26309 | J20: 29469 | K20: =K11+K16+K17+K19 -> 31258.401 | L20: =L11+L16+L17+L19 -> 33839.434 | M20: =M11+M16+M17+M19 -> 36618.187 | N20: =N11+N16+N17+N19 -> 39704.229 | O20: =O11+O16+O17+O19 -> 43303.44 | P20: =P11+P16+P17+P19 -> 47691.363
B22: Taxes | F22: -4756 | G22: -5724 | H22: -5578 | I22: -6152 | J22: -7199 | K22: =K322*-1 -> -7658.3081 | L22: =L322*-1 -> -8290.6613 | M22: =M322*-1 -> -8971.4558 | N22: =N322*-1 -> -9727.5362 | O22: =O322*-1 -> -10609.343 | P22: =P20*'Drivers, Inputs and Outputs'!G20*-1 -> -11684.384
B23: Net Income | F23: 13940 | G23: 11292 | H23: 16270 | I23: 20157 | J23: 22270 | K23: =K20+K22 -> 23600.092 | L23: =L20+L22 -> 25548.773 | M23: =M20+M22 -> 27646.731 | N23: =N20+N22 -> 29976.693 | O23: =O20+O22 -> 32694.097 | P23: =P20+P22 -> 36006.979
B25: Net Income to Controlling Interest | F25: -267 | G25: 388 | H25: -759 | I25: -721 | J25: -377 | K25: =K550 -> -347.2 | L25: =L550 -> -363.24 | M25: =M550 -> -513.488 | N25: =N550 -> -464.3856 | O25: =O550 -> -413.06272 | P25: =P550 -> 0
B26: Net income to parent | F26: 13673 | G26: 11680 | H26: 15511 | I26: 19436 | J26: 21893 | K26: =K23+K25 -> 23252.892 | L26: =L23+L25 -> 25185.533 | M26: =M23+M25 -> 27133.243 | N26: =N23+N25 -> 29512.308 | O26: =O23+O25 -> 32281.035 | P26: =P23+P25 -> 36006.979
B29: Cash flow Statement
B30: All figures in million $
F31: =F3 -> 44592 | G31: =G3 -> 44957 | H31: =H3 -> 45322 | I31: =I3 -> 45688 | J31: =J3 -> 46053 | K31: =K3 -> 46418 | L31: =L3 -> 46783 | M31: =M3 -> 47149 | ... O31: =O3 -> 47879
B33: Consolidated Net Income | F33: 13940 | G33: 11292 | H33: 16270 | I33: 20157 | J33: 22270 | K33: =K26 -> 23252.892 | L33: =L26 -> 25185.533 | M33: =M26 -> 27133.243 | N33: =N26 -> 29512.308 | O33: =O26 -> 32281.035
B34: (+) D&A | F34: 10658 | G34: 10945 | H34: 11853 | I34: 12973 | J34: 14203 | K34: =K245 -> 15634.26 | L34: =L245 -> 18123.288 | M34: =M245 -> 20829.446 | N34: =N245 -> 23777.703 | O34: =O245 -> 26989.376
B35: (+/-) Investment (gains) and losses | F35: -2440 | G35: -1683 | H35: -3193 | I35: -878 | J35: 2016 | K35: 0 | L35: 0 | M35: 0 | N35: 0 | O35: 0
B36: (+/-) losses on Disposal of business ops | F36: 433 | G36: 0 | H36: 0 | I36: 0 | J36: 0 | K36: 0 | L36: 0 | M36: 0 | N36: 0 | O36: 0
B37: (+/-) Deferred Tax | F37: -755 | G37: 449 | H37: -175 | I37: -635 | J37: 2277 | K37: =K321 -> 2095.5285 | L37: =L321 -> 1738.3776 | M37: =M321 -> 1418.2746 | N37: =N321 -> 1095.1217 | O37: =O321 -> 796.23428
B38: (+/-) Loss on Extinguishment of debt | F38: 2410 | G38: 0 | H38: 0 | I38: 0 | J38: 0 | K38: 0 | L38: 0 | M38: 0 | N38: 0 | O38: 0
B39: (+/-) Other Operating items | F39: 1652 | G39: 1919 | H39: 2642 | I39: 2889 | J39: 4079 | K39: =K594 -> 4424.1868 | L39: =L594 -> 5058.6941 | M39: =M594 -> 5749.5927 | N39: =N594 -> 6516.7352 | O39: =O594 -> 7370.7816
B40: (+/-) Change in Receivables, net | F40: -1796 | G40: 240 | H40: -797 | I40: -1106 | J40: -1136 | K40: =K206 -> -332.73478 | L40: =L206 -> -405.71789 | M40: =M206 -> -417.44113 | N40: =N206 -> -459.47994 | O40: =O206 -> -504.82825
B41: (+/-) Change in Inventories | F41: -11764 | G41: -528 | H41: 2017 | I41: -2755 | J41: -1443 | K41: =K207 -> -2781.5077 | L41: =L207 -> -2478.7521 | M41: =M207 -> -2575.7968 | N41: =N207 -> -2840.669 | O41: =O207 -> -3129.4954
B42: (+/-) Change in Accounts Payable | F42: 5520 | G42: -1425 | H42: 2515 | I42: 3228 | J42: 1611 | K42: =K208 -> 2038.3363 | L42: =L208 -> 3881.1331 | M42: =M208 -> 3691.3231 | N42: =N208 -> 4531.0717 | O42: =O208 -> 5014.5175
B43: (+/-) Change in Prepaid Expenses | G43: =F84-G84 -> -1002 | H43: =G84-H84 -> -801 | I43: =H84-I84 -> -689 | J43: =I84-J84 -> -113 | K43: =J84-K84 -> -241.63596 | L43: =K84-L84 -> -506.82195 | M43: =L84-M84 -> -435.38525 | N43: =M84-N84 -> -603.3013 | O43: =N84-O84 -> -926.67098
B44: (+/-) Change in Other assets | G44: =F91-G91 -> 2018 | H44: =G91-H91 -> 3063 | I44: =H91-I91 -> 4202 | J44: =I91-J91 -> -1234 | K44: =J91-K91 -> -1269.1746 | L44: =K91-L91 -> -1226.6653 | M44: =L91-M91 -> -1316.5576 | N44: =M91-N91 -> -1458.6801 | O44: =N91-O91 -> -1618.6549
B45: (+/-) Accrued Liabilities | F45: 1404 | G45: 4393 | H45: -1324 | I45: 379 | J45: 1607 | K45: =K97-J97 -> 1409.058 | L45: =L97-K97 -> 1568.4783 | M45: =M97-L97 -> 1648.2687 | N45: =N97-M97 -> 1821.3154 | O45: =O97-N97 -> 2012.187
B46: (+/-) Accrued Income Taxes | F46: 39 | G46: -127 | H46: -468 | I46: 435 | J46: 113 | K46: =K98-J98 -> 93.247733 | L46: =L98-K98 -> 56.911784 | M46: =M98-L98 -> 83.700145 | N46: =N98-M98 -> 69.937438 | O46: =O98-N98 -> 108.09047
B47: Cash Flow from Operations | F47: 24181 | G47: 28841 | H47: 35726 | I47: 36443 | J47: 41565 | K47: =SUM(K33:K46) -> 44322.456 | L47: =SUM(L33:L46) -> 50994.458 | M47: =SUM(M33:M46) -> 55808.668 | N47: =SUM(N33:N46) -> 61962.062 | O47: =SUM(O33:O46) -> 68392.572
B49: (-) Net CapEx | F49: -13106 | G49: -16857 | H49: -20606 | I49: -23783 | J49: -26642 | K49: =K257*-1 -> -28119.832 | L49: =L257*-1 -> -31616.838 | M49: =M257*-1 -> -33330.972 | N49: =N257*-1 -> -37427.195 | O49: =O257*-1 -> -39652.939
B50: (+) Disposal Proceeds of PP&E | F50: 394 | G50: 170 | H50: 250 | I50: 432 | J50: 106 | K50: =K576 -> 309.31815 | L50: =L576 -> 363.59364 | M50: =M576 -> 399.97167 | N50: =N576 -> 467.83994 | O50: =O576 -> 515.48821
B51: (+) Disposal Proceds from Strategic Divestitures | F51: 7935 | G51: 0 | H51: 135 | I51: 4080 | J51: 927 | K51: =K577 -> 0 | L51: =L577 -> 0 | M51: =M577 -> 0 | N51: =N577 -> 0 | O51: =O577 -> 0
B52: (-) Payments to Acquisitions, net of cash aquired | F52: -359 | G52: -740 | H52: -9 | I52: -1896 | J52: -53 | K52: =K578 -> 0 | L52: =L578 -> 0 | M52: =M578 -> 0 | N52: =N578 -> 0 | O52: =O578 -> 0
B53: (-) Other Investing Activities | F53: -879 | G53: -295 | H53: -1057 | I53: -212 | J53: -688 | K53: =K600 -> -751.8928 | L53: =L600 -> -616.22284 | M53: =M600 -> -843.89938 | N53: =N600 -> -1231.6114 | O53: =O600 -> -1474.6177
B54: Cash Flow From Investing | F54: -6015 | G54: -17722 | H54: -21287 | I54: -21379 | J54: -26350 | K54: =SUM(K49:K53) -> -28562.406 | L54: =SUM(L49:L53) -> -31869.467 | M54: =SUM(M49:M53) -> -33774.9 | N54: =SUM(N49:N53) -> -38190.967 | O54: =SUM(O49:O53) -> -40612.069
B56: (+/-) Net change in Short term borrowings | F56: 193 | G56: -34 | H56: 512 | I56: 2212 | J56: 3523 | K56: =K395 -> 0 | L56: =L395 -> 0 | M56: =M395 -> 0 | N56: =N395 -> 0 | O56: =O395 -> 0
B57: (+) Proceeds from issuance of Long term debt | F57: 6945 | G57: 5041 | H57: 4967 | I57: 0 | J57: 3983 | K57: =K569 -> 4427.5 | L57: =L569 -> 4046.25 | M57: =M569 -> 4236.25 | N57: =N569 -> 2678.75 | O57: =O569 -> 3250
B58: (-) Repyaments of Long term debt | F58: -13010 | G58: -2689 | H58: -4217 | I58: -3468 | J58: -2625 | K58: =Notes!B73*-1 -> -3542 | L58: =Notes!B74*-1 -> -3237 | M58: =Notes!B75*-1 -> -3389 | N58: =Notes!B76*-1 -> -2143 | O58: =Notes!B77*-1 -> -2600
B59: (-) Premium paid to Extinguish Debt | F59: -2317 | G59: 0 | H59: 0 | I59: 0 | J59: 0 | K59: 0 | L59: 0 | M59: 0 | N59: 0 | O59: 0
B60: (-) Common Dividends | F60: -6152 | G60: -6114 | H60: -6140 | I60: -6688 | J60: -7507 | K60: =K444*-1 -> -7905.9834 | L60: =L444*-1 -> -8500.1172 | M60: =M444*-1 -> -9089.6364 | N60: =N444*-1 -> -9812.8423 | O60: =O444*-1 -> -10652.741
B61: (-) Stock repurchse | F61: -9787 | G61: -9920 | H61: -2779 | I61: -4494 | J61: -8088 | K61: =K465*-1 -> -5242.6007 | L61: =L465*-1 -> -6751.457 | M61: =M465*-1 -> -8205.8896 | N61: =N465*-1 -> -8485.3873 | O61: =O465*-1 -> -1314.6653
B62: (+/-) Net NCI Transaction | F62: 2815 | G62: -1205 | H62: -3509 | I62: -214 | J62: -328 | K62: =K592 -> -173.6 | L62: =L592 -> -181.62 | M62: =M592 -> -256.744 | N62: =N592 -> -232.1928 | O62: =O592 -> -206.53136
B63: (+/-) Other Financing activities | F63: -1515 | G63: -2118 | H63: -2248 | I63: -2170 | J63: -2511 | K63: =K597 -> -2699.5038 | L63: =L597 -> -2885.0365 | M63: =M597 -> -3124.7786 | N63: =N597 -> -3478.5276 | O63: =O597 -> -4058.5949
B64: Total cash Flow from Financing | F64: -22828 | G64: -17039 | H64: -13414 | I64: -14822 | J64: -13553 | K64: =SUM(K56:K63) -> -15136.188 | L64: =SUM(L56:L63) -> -17508.981 | M64: =SUM(M56:M63) -> -19829.799 | N64: =SUM(N56:N63) -> -21473.2 | O64: =SUM(O56:O63) -> -15582.533
B66: FX rate effect | F66: -140 | G66: -73 | H66: 69 | I66: -641 | J66: 123 | K66: 0 | L66: 0 | M66: 0 | N66: 0 | O66: 0 | R66: FX rates are quite unpredictable and dependency on Market movements, here we are focusing on the company not its equity investments are hedging strategies
B68: Cash Balance :
B69: Beginning of the Year | F69: 17788 | G69: 14834 | H69: 8841 | I69: 9935 | J69: 9536 | K69: =J71 -> 11321 | L69: =K71 -> 11944.862 | M69: =L71 -> 13560.872 | N69: =M71 -> 15764.841 | O69: =N71 -> 18062.737
B70: Increase/(Decrease) | F70: =F64+F54+F47+F66 -> -4802 | G70: =G64+G54+G47+G66 -> -5993 | H70: =H64+H54+H47+H66 -> 1094 | I70: =I64+I54+I47+I66 -> -399 | J70: =J64+J54+J47+J66 -> 1785 | K70: =K47+K54+K64 -> 623.86203 | L70: =L47+L54+L64 -> 1616.0099 | M70: =M47+M54+M64 -> 2203.9694 | N70: =N47+N54+N64 -> 2297.8953 | O70: =O47+O54+O64 -> 12197.97
B71: Ending of the Year | F71: 14834 | G71: 8841 | H71: 9935 | I71: 9536 | J71: 11321 | K71: =SUM(K69:K70) -> 11944.862 | L71: =SUM(L69:L70) -> 13560.872 | M71: =SUM(M69:M70) -> 15764.841 | N71: =SUM(N69:N70) -> 18062.737 | O71: =SUM(O69:O70) -> 30260.706
B73: since cfs cash has RC but BS cash does not
B74: Restricted cash | F74: =F71-F81 -> 74 | G74: =G71-G81 -> 216 | H74: =H71-H81 -> 68 | I74: =I71-I81 -> 499 | J74: =J71-J81 -> 594 | K74: 540 | L74: 540 | M74: 540 | N74: 540 | O74: 540 | R74: Assuming the RC will average of the previous two years at 540 Millions, as prior years are more volatile
R75: And also due to lack of Information on RC we assumed total Cash will directly flows into BS from CFS
B77: Balance Sheet
B78: All figures in million $
F79: =F31 -> 44592 | G79: =G31 -> 44957 | H79: =H31 -> 45322 | I79: =I31 -> 45688 | J79: =J31 -> 46053 | K79: =K31 -> 46418 | L79: =L31 -> 46783 | M79: =M31 -> 47149 | ... O79: =O31 -> 47879
B80: Assets:
B81: Cash & Equivalents | F81: 14760 | G81: 8625 | H81: 9867 | I81: 9037 | J81: 10727 | K81: =K71 -> 11944.862 | L81: =L71 -> 13560.872 | M81: =M71 -> 15764.841 | N81: =N71 -> 18062.737 | O81: =O71 -> 30260.706
B82: Account Receivables | F82: 8280 | G82: 7933 | H82: 8796 | I82: 9975 | J82: 11172 | K82: =K200 -> 11504.735 | L82: =L200 -> 11910.453 | M82: =M200 -> 12327.894 | N82: =N200 -> 12787.374 | O82: =O200 -> 13292.202
B83: Inventory | F83: 56511 | G83: 56576 | H83: 54892 | I83: 56435 | J83: 58851 | K83: =K201 -> 61632.508 | L83: =L201 -> 64111.26 | M83: =M201 -> 66687.057 | N83: =N201 -> 69527.726 | O83: =O201 -> 72657.221
B84: Prepaid expenses and Other | F84: 1519 | G84: 2521 | H84: 3322 | I84: 4011 | J84: 4124 | K84: =K552 -> 4365.636 | L84: =L552 -> 4872.4579 | M84: =M552 -> 5307.8432 | N84: =N552 -> 5911.1445 | O84: =O552 -> 6837.8154
B87: PP&E | F87: 94515 | G87: 100760 | H87: 110810 | I87: 119993 | J87: 136083 | K87: =K270 -> 148259.25 | L87: =L270 -> 161389.21 | M87: =M270 -> 173490.76 | N87: =N270 -> 186672.42 | O87: =O270 -> 198820.49
B88: Op. lease assets | F88: 13758 | G88: 13555 | H88: 13673 | I88: 13599 | J88: 14750 | K88: =K517 -> 15694.249 | L88: =L517 -> 15664.646 | M88: =M517 -> 15754.542 | N88: =N517 -> 16036.118 | O88: =O517 -> 16618.603
B89: Finance lease assets | F89: 4351 | G89: 4919 | H89: 5855 | I89: 6112 | J89: 6123 | K89: =K523 -> 6318.1702 | L89: =L523 -> 6548.1928 | M89: =M523 -> 6842.9512 | N89: =N523 -> 7239.5629 | O89: =O523 -> 7787.8059
B90: Goodwill | F90: 29014 | G90: 28174 | H90: 28113 | I90: 28792 | J90: 28735 | K90: =K272 -> 28878.675 | L90: =L272 -> 29023.068 | M90: =M272 -> 29168.184 | N90: =N272 -> 29314.025 | O90: =O272 -> 29460.595 | R90: Assumed the average for Goodwill as its bit constant in 28 Billion range from past 4 years
B91: Other assets | F91: 22152 | G91: 20134 | H91: 17071 | I91: 12869 | J91: 14103 | K91: =K556 -> 15372.175 | L91: =L556 -> 16598.84 | M91: =M556 -> 17915.398 | N91: =N556 -> 19374.078 | O91: =O556 -> 20992.732
B92: Total Assets | F92: 244860 | G92: 243197 | H92: 252399 | I92: 260823 | J92: 284668 | K92: =SUM(K81:K91) -> 303970.26 | L92: =SUM(L81:L91) -> 323679 | M92: =SUM(M81:M91) -> 343259.47 | N92: =SUM(N81:N91) -> 364925.18 | O92: =SUM(O81:O91) -> 396728.17
B94: Liabilities:
B95: Short term Borrowings | F95: 410 | G95: 372 | H95: 878 | I95: 3068 | J95: 6596 | K95: =K396 -> 6596 | L95: =L396 -> 6596 | M95: =M396 -> 6596 | N95: =N396 -> 6596 | O95: =O396 -> 6596
B96: Accounts Payable | F96: 55261 | G96: 53742 | H96: 56812 | I96: 58666 | J96: 63061 | K96: =K202 -> 65099.336 | L96: =L202 -> 68980.469 | M96: =M202 -> 72671.792 | N96: =N202 -> 77202.864 | O96: =O202 -> 82217.382
B97: Accrued Liabilities | F97: 26060 | G97: 31126 | H97: 28759 | I97: 29345 | J97: 31187 | K97: =K559 -> 32596.058 | L97: =L559 -> 34164.536 | M97: =M559 -> 35812.805 | N97: =N559 -> 37634.12 | O97: =O559 -> 39646.307
B98: Accrued Income Taxes | F98: 851 | G98: 727 | H98: 307 | I98: 608 | J98: 596 | K98: =K563 -> 689.24773 | L98: =L563 -> 746.15952 | M98: =M563 -> 829.85966 | N98: =N563 -> 899.7971 | O98: =O563 -> 1007.8876
B99: Revolving Credit line | F99: 0 | G99: 0 | H99: 0 | I99: 0 | J99: 0 | K99: =K420 -> 0 | L99: =L420 -> 0 | M99: =M420 -> 0 | N99: =N420 -> 0 | O99: =O420 -> 0
B101: LT Debt | F101: =Notes!E196 -> 37667 | G101: =Notes!F196 -> 38840 | H101: =Notes!G196 -> 39579 | I101: =Notes!H196 -> 35999 | J101: =Notes!I196 -> 38166 | K101: =K388 -> 39051.5 | L101: =L388 -> 39860.75 | M101: =M388 -> 40708 | N101: =N388 -> 41243.75 | O101: =O388 -> 41893.75
B102: Total Op Lease Obligations | F102: =Notes!E187 -> 14492 | G102: =Notes!F187 -> 14301 | H102: =Notes!G187 -> 14430 | I102: =Notes!H187 -> 14324 | J102: =Notes!I187 -> 15572 | K102: =K531 -> 16637.629 | L102: =L531 -> 17849.031 | M102: =M531 -> 19268.825 | N102: =N531 -> 20986.473 | O102: =O531 -> 23135.21
B103: Total Finance lease Obligations | F103: =Notes!E191 -> 4754 | G103: =Notes!F191 -> 5410 | H103: =Notes!G191 -> 6434 | I103: =Notes!H191 -> 6723 | J103: =Notes!I191 -> 6761 | K103: =K538 -> 7053.055 | L103: =L538 -> 7380.6612 | M103: =M538 -> 7758.0633 | N103: =N538 -> 8206.6546 | O103: =O538 -> 8759.7219
B104: Deferred Tax and Other | F104: 13474 | G104: 14688 | H104: 14629 | I104: 14398 | J104: 16549 | K104: =K573 -> 18644.528 | L104: =L573 -> 20382.906 | M104: =M573 -> 21801.181 | N104: =N573 -> 22896.302 | O104: =O573 -> 23692.537
B105: Total Liabilities | F105: 152969 | G105: 159206 | H105: 161828 | I105: 163131 | J105: 178488 | K105: =SUM(K95:K104) -> 186367.35 | L105: =SUM(L95:L104) -> 195960.51 | M105: =SUM(M95:M104) -> 205446.53 | N105: =SUM(N95:N104) -> 215665.96 | O105: =SUM(O95:O104) -> 226948.8
B107: Other Items / Balancing Items
B109: Redeemable NCI | F109: 0 | G109: 237 | H109: 222 | I109: 271 | J109: 293 | K109: 293 | L109: 293 | M109: 293 | N109: 293 | O109: 293 | R109: Average of previous years at 256
B111: Equity:
B112: Common Stock | F112: 276 | G112: 808 | H112: 805 | I112: 802 | J112: 797 | K112: =J112 -> 797 | L112: =K112 -> 797 | M112: =L112 -> 797 | N112: =M112 -> 797 | O112: =N112 -> 797
B113: Capital in Excess of Par value | F113: 4839 | G113: 4430 | H113: 4544 | I113: 5503 | J113: 6816 | K113: =J113 -> 6816 | L113: =K113 -> 6816 | M113: =L113 -> 6816 | N113: =M113 -> 6816 | O113: =N113 -> 6816
B114: Retained Earnings | F114: 86904 | G114: 83135 | H114: 89814 | I114: 98313 | J114: 104774 | K114: =K453 -> 114878.31 | L114: =L453 -> 124812.27 | M114: =M453 -> 134649.98 | N114: =N453 -> 145864.06 | O114: =O453 -> 166177.69
B115: Accumulated Other Comprehensive Loss | F115: -8766 | G115: -11680 | H115: -11302 | I115: -13605 | J115: -12770 | K115: =K468 -> -11625 | L115: =L468 -> -11625 | M115: =M468 -> -11625 | N115: =N468 -> -11625 | O115: =O468 -> -11625
B116: Walmart Shareholders Equity | F116: 83253 | G116: 76693 | H116: 83861 | I116: 91013 | J116: 99617 | K116: =SUM(K112:K115) -> 110866.31 | L116: =SUM(L112:L115) -> 120800.27 | M116: =SUM(M112:M115) -> 130637.98 | N116: =SUM(N112:N115) -> 141852.06 | O116: =SUM(O112:O115) -> 162165.69
B117: Nonredeemable NCI | F117: 8638 | G117: 7061 | H117: 6488 | I117: 6408 | J117: 6270 | K117: =K474 -> 6443.6 | L117: =L474 -> 6625.22 | M117: =M474 -> 6881.964 | N117: =N474 -> 7114.1568 | O117: =O474 -> 7320.6882
B118: Total Equity | F118: 91891 | G118: 83754 | H118: 90349 | I118: 97421 | J118: 105887 | K118: =SUM(K116:K117) -> 117309.91 | L118: =SUM(L116:L117) -> 127425.49 | M118: =SUM(M116:M117) -> 137519.95 | N118: =SUM(N116:N117) -> 148966.22 | O118: =SUM(O116:O117) -> 169486.38
B120: Total Liabilities + Equity | F120: =F118+F105+F109 -> 244860 | G120: =G118+G105+G109 -> 243197 | H120: =H118+H105+H109 -> 252399 | I120: =I118+I105+I109 -> 260823 | J120: =J118+J105+J109 -> 284668 | K120: =K118+K105+K109 -> 303970.26 | L120: =L118+L105+L109 -> 323679 | M120: =M118+M105+M109 -> 343259.47 | ... O120: =O118+O105+O109 -> 396728.17
B122: Balance Check | F122: =F92-F120 -> 0 | G122: =G92-G120 -> 0 | H122: =H92-H120 -> 0 | I122: =I92-I120 -> 0 | J122: =J92-J120 -> 0 | K122: =K92-K120 -> 0.00042136456 | L122: =L92-L120 -> 4.2726344e-05 | M122: =M92-M120 -> 2.2770604e-05 | ... O122: =O92-O120 -> 0.0002975461
B125: Revenue Schedule
B126: All figures in million $
...

Sheet Notes
A1: Property and Equipment
B2: Estimated useful years
B3: (in years) | C3: 44592 | D3: 44957 | E3: 45322 | F3: 45688 | G3: 46053
A4: Land | B4: N/A | C4: 19204 | D4: 19317 | E4: 19562 | F4: 19342 | G4: 20754
A5: Buildings and improvements | B5: 3 to 40 | C5: 100376 | D5: 104554 | E5: 111767 | F5: 117973 | G5: 128472
A6: Fixtures and Equipments | B6: 2 to 30 | C6: 60282 | D6: 65235 | E6: 72161 | F6: 76226 | G6: 85539 | I6: =231617-19342-15403 -> 196872
A7: Transportation equipment | B7: 3 to 15 | C7: 2263 | D7: 2462 | E7: 2979 | F7: 2673 | G7: 2928
A8: Construction in progress | B8: N/A | C8: 7199 | D8: 10802 | E8: 13390 | F8: 15403 | G8: 18728 | I8: =G9-G4-G8 -> 216939
A9: PP&E | C9: 189324 | D9: 202370 | E9: 219859 | F9: 231617 | G9: 256421
A10: Accumulated depreciation | C10: -94809 | D10: -101610 | E10: -109049 | F10: -111624 | G10: -120338
A11: PPE&E, net | C11: 94515 | D11: 100760 | E11: 110810 | F11: 119993 | G11: 136083 | I11: =G11-G4-G8 -> 96601 | J11: =I11-(G28/24.5%) -> 71613.245
A15: Deferred Taxes
C16: 2022 | D16: 2023 | E16: 2024 | F16: 2025 | G16: 2026
A17: (Amounts in millions)
A18: Deferred tax assets:
A19: Loss and tax credit carryforwards | C19: 9456 | D19: 7690 | E19: 7136 | F19: 7539 | G19: 4615
A20: Accrued liabilities | C20: 2752 | D20: 3312 | E20: 3066 | F20: 3009 | G20: 3504
A21: Share-based compensation | C21: 231 | D21: 237 | E21: 238 | F21: 263 | G21: 0
A22: Lease obligations | C22: 4320 | D22: 4653 | E22: 4831 | F22: 4611 | G22: 5181
A23: Other | C23: 893 | D23: 839 | E23: 1124 | F23: 1076 | G23: 1239 | H23: In 2026 the other line itme here may contain share based compensation as it is omitted form th eactual notes for 2026 report.
A24: Total deferred tax assets | C24: 17652 | D24: 16731 | E24: 16395 | F24: 16498 | G24: 14539
A25: Valuation allowances | C25: -9542 | D25: -7815 | E25: -7485 | F25: -7405 | G25: -4421
A26: Deferred tax assets, net of valuation allowances | C26: 8110 | D26: 8916 | E26: 8910 | F26: 9093 | G26: 10118
A27: Deferred tax liabilities:
A28: Property and equipment | C28: 4414 | D28: 4352 | E28: 4813 | F28: 4303 | G28: 6122
A29: Acquired intangibles | C29: 1065 | D29: 932 | E29: 898 | F29: 1096 | G29: 1066
A30: Inventory | C30: 1588 | D30: 3032 | E30: 3035 | F30: 3336 | G30: 3570
A31: Lease right of use assets | C31: 4355 | D31: 4727 | E31: 4941 | F31: 4816 | G31: 5345
A32: Mark-to-market investments | C32: 1825 | D32: 1390 | E32: 322 | F32: 353 | G32: 0 | H32: Same as Share based Compensation, Mark to Market is clubbed with the other making others 460 to 813 in value
A33: Other | C33: 307 | D33: 249 | E33: 486 | F33: 460 | G33: 1373
A34: Total deferred tax liabilities | C34: 13554 | D34: 14682 | E34: 14495 | F34: 14364 | G34: 17476
A35: Net deferred tax liabilities | C35: 5444 | D35: 5766 | E35: 5585 | F35: 5271 | G35: 7358
A38: Short Term Borrowings and Long Term Debt
A40: Short-term borrowings consist of commercial paper and lines of credit.
A41: Short-term borrowings as of January 31, 2025 and 2024 were $3.1 billion and $0.9 billion, respectively, with weighted-average interest rates of 5.3% and 7.7%, respectively.
A42: Short-term borrowings as of January 31, 2026 and 2025 were $6.6 billion and $3.1 billion, respectively, with weighted-average interest rates of 4% and 5.3%, respectively.
A43: committed line of credit in US to support Commercial Paper program | D43: Jan 31st 2024 | G43: Jan 31st 2025
D44: Available | E44: drawn | F44: Undrawn | G44: Available | H44: drawn | I44: Undrawn | J44: same with 2026 year as the 2025 year
A45: Five year credit facility | D45: 5000 | E45: 0 | F45: 5000 | G45: 5000 | H45: 0 | I45: 5000 | J45: same balaces foe 2023, 2022
A46: 364- days revolving credit facility | D46: 10000 | E46: 0 | F46: 10000 | G46: 10000 | H46: 0 | I46: 10000
A47: Total | D47: 15000 | E47: 0 | F47: 15000 | G47: 15000 | H47: 0 | I47: 15000
A50: Long term debt | E50: Jan 31st 2024 | G50: Jan 31st 2025 | I50: Jan 31st 2026
B51: Maturity dates by FY | E51: amount | F51: Avg rate | G51: amount | H51: Avg rate | I51: amount | J51: Avg rate
A52: Unsecured fixed rate debt
A53: Fixed | B53: 2027 to 2054 (for latest year as Ref) | E53: 34527 | F53: 0.037 | G53: 31406 | H53: 0.038 | I53: 32032 | J53: 0.039
A54: Variable | B54: year 2028 | E54: 0 | F54: 0 | G54: 0 | H54: 0 | I54: 750 | J54: 0.041
A55: Total USD denominated | E55: 34527 | F55: 0.037 | G55: 31406 | I55: 32782
A56: Euro denominated | B56: 2027 to 2030 | E56: 1789 | F56: 0.04 | G56: 1715 | H56: 0.04 | I56: 1955 | J56: 0.04
A57: Sterling denominated | B57: 2031 to 2039 | E57: 3412 | F57: 0.054 | G57: 3336 | H57: 0.054 | I57: 3677 | J57: 0.054
A58: Yen denominated | B58: year 2028 | E58: 677 | F58: 0.004 | G58: 389 | H58: 0.005 | I58: 388 | J58: 0.005
A59: Total Unsecured fixed rate debt | E59: 40405 | G59: 36846 | I59: 38802
A60: total other | E60: -826 | G60: -847 | I60: -636
A61: Total debt | E61: 39579 | G61: 35999 | I61: 38166
A62: (-) amounts due within one year | E62: -3447 | G62: -2598 | I62: -3542
A63: Long term debt | E63: 36132 | G63: 33401 | I63: 34624
A66: Annual maturities of long-term debt during the next five years and thereafter are as follows
A68: (Amounts in millions)
A69: Annual Fiscal Year Maturties
A70: 2024 | B70: 4191 | C70: From 23 AR
A71: 2025 | B71: 3447 | C71: From 24 AR
A72: 2026 | B72: 2598 | C72: From 25 AR
A73: 2027 | B73: 3542 | C73: From 26 AR
A74: 2028 | B74: 3237
A75: 2029 | B75: 3389
A76: 2030 | B76: 2143
A77: 2031 | B77: 2600
A78: Thereafter | B78: 23255
A79: Total | B79: =SUM(B73:B78) -> 38166
A81: Weighted average interest rate long term debt | B81: =(31406/36846)*3.8%+(1715/36846)*4%+(3336/36846)*5.4%+(389/36846)*0.5% -> 0.039193318
A83: Debt issuances
A85: There were no long-term debt issuances in fiscal 2025. Information on significant long-term debt issued during fiscal 2024, for general corporate purposes
A87: Issue Date | B87: Princiapal amount | E87: maturity date | F87: Fixed vs Floating | G87: Interest Rate | H87: Net Proceeds
A88: April 18, 2023 | B88: 750 | E88: April 15, 2026 | F88: Fixed | G88: 0.04 | H88: 748
A89: April 18, 2023 | B89: 750 | E89: April 15, 2028 | F89: Fixed | G89: 0.039 | H89: 746
A90: April 18, 2023 | B90: 500 | E90: April 15, 2030 | F90: Fixed | G90: 0.04 | H90: 497
A91: April 18, 2023 | B91: 1500 | E91: April 15, 2033 | F91: Fixed | G91: 0.041 | H91: 1491
A92: April 18, 2023 | B92: 1500 | E92: April 15, 2053 | F92: Fixed | G92: 0.045 | H92: 1485
A93: Total | H93: 4967
A96: Information on significant issuances of longterm debt during fiscal 2026, for general corporate purposes, is as follows
A98: Issue Date | B98: Princiapal amount | E98: maturity date | F98: Fixed vs Floating | G98: Interest Rate | H98: Net Proceeds
A99: April 18, 2025 | B99: 750 | E99: April 28, 2027 | F99: Floating | G99: Floating | H99: 749
A100: April 18, 2025 | B100: 750 | E100: April 28, 2027 | F100: Fixed | G100: 0.041 | H100: 748
A101: April 18, 2025 | B101: 500 | E101: April 28, 2030 | F101: Fixed | G101: 0.0435 | H101: 993
A102: April 18, 2025 | B102: 1500 | E102: April 28, 2035 | F102: Fixed | G102: 0.049 | H102: 1493
A103: Total | H103: 3883
A107: Walmart U.S. net sales by merchandise category | B107: Fiscal Years Ended January 31,
B108: 2023 | C108: 2023 | D108: 2024 | E108: 2025 | F108: 2026
A109: Grocery | B109: 218944 | C109: 247299 | D109: 264210 | E109: 276003 | F109: 285482
A110: General merchandise | B110: 125876 | C110: 118597 | D110: 113985 | E110: 113921 | F110: 115060
A111: Health and wellness | B111: 42839 | C111: 46591 | D111: 54898 | E111: 62092 | F111: 69547
A112: Other | B112: 5588 | C112: 8066 | D112: 8724 | E112: 10399 | F112: 12886
A113: Total | B113: 393247 | C113: 420553 | D113: 441817 | E113: 462415 | F113: 482975
A116: Walmart International net sales by market
B117: 2022 | C117: 2023 | D117: 2024 | E117: 2025 | F117: 2026
A118: Mexico and Central America | B118: 35964 | C118: 40496 | D118: 49726 | E118: 51970 | F118: 52492
A119: Canada | B119: 21773 | C119: 22300 | D119: 22639 | E119: 23035 | F119: 23724
A120: China | B120: 13852 | C120: 14711 | D120: 17011 | E120: 19975 | F120: 24623
A121: United Kingdom | B121: 3811 | C121: 0 | D121: 0 | E121: 0 | F121: 0
A122: Other | B122: 25559 | C122: 23476 | D122: 25265 | E122: 26905 | F122: 29584
A123: Total | B123: 100959 | C123: 100983 | D123: 114641 | E123: 121885 | F123: 130423
...
